the_weather/__init__.py
the_weather/test.py
the_weather/weather.py
the_weather-1.5.dist-info/LICENSE
the_weather-1.5.dist-info/METADATA
the_weather-1.5.dist-info/WHEEL
the_weather-1.5.dist-info/top_level.txt
the_weather-1.5.dist-info/RECORD
