Metadata-Version: 2.1
Name: the_weather
Version: 1.5
Summary: Package for getting weather data based on a zipcode
Home-page: https://github.com/michaelMondoro/the_weather
Author: Michael Mondoro
Author-email: michaelmondoro@gmail.com
Classifier: Programming Language :: Python :: 3
Classifier: License :: OSI Approved :: MIT License
Classifier: Operating System :: OS Independent
Requires-Python: >=3.7
License-File: LICENSE
